torchModelSummary/__init__.py
torchModelSummary/layerInfo.py
torchModelSummary/torchModelSummary.py
torchModelSummary-1.0.2.dist-info/LICENSE
torchModelSummary-1.0.2.dist-info/METADATA
torchModelSummary-1.0.2.dist-info/WHEEL
torchModelSummary-1.0.2.dist-info/top_level.txt
torchModelSummary-1.0.2.dist-info/RECORD
