Metadata-Version: 2.2
Name: torchModelSummary
Version: 1.0.2
Summary: A custom-renovated version of torchsummary module
Home-page: https://github.com/DaunKimY/torchModelSummary
Author: Daun Kim
Author-email: daunkim430@yonsei.ac.kr
License: MIT
Keywords: torchModelSummary,torch,pytorch,model,summary,statistics
Classifier: Programming Language :: Python :: 3
Classifier: License :: OSI Approved :: MIT License
Classifier: Operating System :: OS Independent
Requires-Python: >=3.6
License-File: LICENSE
Requires-Dist: torch
Dynamic: author
Dynamic: author-email
Dynamic: classifier
Dynamic: description
Dynamic: description-content-type
Dynamic: home-page
Dynamic: keywords
Dynamic: license
Dynamic: requires-dist
Dynamic: requires-python
Dynamic: summary
